<XBRL>
<?xml version="1.0" encoding="utf-8"?>
<InstanceReport xmlns:xsi="http://www.w3.org/2001/XMLSchema-instance" xmlns:xsd="http://www.w3.org/2001/XMLSchema">
  <Version>2.0.0.10</Version>
  <hasSegments>false</hasSegments>
  <ReportName>Employees Defined Contribution Plan</ReportName>
  <ReportLongName>0614 - Disclosure - Employees Defined Contribution Plan</ReportLongName>
  <DisplayLabelColumn>true</DisplayLabelColumn>
  <ShowElementNames>false</ShowElementNames>
  <RoundingOption />
  <HasEmbeddedReports>false</HasEmbeddedReports>
  <Columns>
    <Column>
      <LabelColumn>false</LabelColumn>
      <Id>1</Id>
      <Labels>
        <Label Id="1" Label="12 Months Ended" />
        <Label Id="2" Label="Jan. 30, 2010" />
      </Labels>
      <CurrencyCode>usd</CurrencyCode>
      <CurrencySymbol>$</CurrencySymbol>
      <FootnoteIndexer />
      <hasSegments>false</hasSegments>
      <hasScenarios>false</hasScenarios>
      <Segments />
      <Scenarios />
      <Units>
        <Unit>
          <UnitID>Shares</UnitID>
          <UnitType>Standard</UnitType>
          <StandardMeasure>
            <MeasureSchema>http://www.xbrl.org/2003/instance</MeasureSchema>
            <MeasureValue>shares</MeasureValue>
            <MeasureNamespace>xbrli</MeasureNamespace>
          </StandardMeasure>
          <Scale>0</Scale>
        </Unit>
        <Unit>
          <UnitID>USD</UnitID>
          <UnitType>Standard</UnitType>
          <StandardMeasure>
            <MeasureSchema>http://www.xbrl.org/2003/iso4217</MeasureSchema>
            <MeasureValue>USD</MeasureValue>
            <MeasureNamespace>iso4217</MeasureNamespace>
          </StandardMeasure>
          <Scale>0</Scale>
        </Unit>
        <Unit>
          <UnitID>USDEPS</UnitID>
          <UnitType>Divide</UnitType>
          <NumeratorMeasure>
            <MeasureSchema>http://www.xbrl.org/2003/iso4217</MeasureSchema>
            <MeasureValue>USD</MeasureValue>
            <MeasureNamespace>iso4217</MeasureNamespace>
          </NumeratorMeasure>
          <DenominatorMeasure>
            <MeasureSchema>http://www.xbrl.org/2003/instance</MeasureSchema>
            <MeasureValue>shares</MeasureValue>
            <MeasureNamespace>xbrli</MeasureNamespace>
          </DenominatorMeasure>
          <Scale>0</Scale>
        </Unit>
      </Units>
    </Column>
  </Columns>
  <Rows>
    <Row>
      <Id>2</Id>
      <Label>Employees' Defined Contribution Plan [Abstract]</Label>
      <Level>0</Level>
      <ElementName>us-gaap_DefinedBenefitPensionPlansAndDefinedBenefitPostretirementPlansDisclosureAbstract</ElementName>
      <ElementPrefix>us-gaap</ElementPrefix>
      <IsBaseElement>true</IsBaseElement>
      <BalanceType>na</BalanceType>
      <PeriodType>duration</PeriodType>
      <ElementDataType>string</ElementDataType>
      <ShortDefinition>No definition available.</ShortDefinition>
      <IsReportTitle>false</IsReportTitle>
      <IsSegmentTitle>false</IsSegmentTitle>
      <IsSubReportEnd>false</IsSubReportEnd>
      <IsCalendarTitle>false</IsCalendarTitle>
      <IsTuple>false</IsTuple>
      <IsAbstractGroupTitle>true</IsAbstractGroupTitle>
      <IsEquityPrevioslyReportedAsRow>false</IsEquityPrevioslyReportedAsRow>
      <IsEquityAdjustmentRow>false</IsEquityAdjustmentRow>
      <IsBeginningBalance>false</IsBeginningBalance>
      <IsEndingBalance>false</IsEndingBalance>
      <IsReverseSign>false</IsReverseSign>
      <PreferredLabelRole />
      <IsEPS>false</IsEPS>
      <FootnoteIndexer />
      <Cells>
        <Cell>
          <Id>1</Id>
          <ShowCurrencySymbol>false</ShowCurrencySymbol>
          <IsNumeric>false</IsNumeric>
          <IsRatio>false</IsRatio>
          <DisplayZeroAsNone>false</DisplayZeroAsNone>
          <NumericAmount>0</NumericAmount>
          <RoundedNumericAmount>0</RoundedNumericAmount>
          <NonNumbericText />
          <NonNumericTextHeader />
          <FootnoteIndexer />
          <hasSegments>false</hasSegments>
          <hasScenarios>false</hasScenarios>
          <DisplayDateInUSFormat>false</DisplayDateInUSFormat>
        </Cell>
      </Cells>
      <OriginalInstanceReportColumns />
      <ElementDefenition>No definition available.</ElementDefenition>
      <IsTotalLabel>false</IsTotalLabel>
    </Row>
    <Row>
      <Id>3</Id>
      <Label>Employees' Defined Contribution Plan</Label>
      <Level>1</Level>
      <ElementName>us-gaap_ScheduleOfDefinedBenefitPlansDisclosuresTextBlock</ElementName>
      <ElementPrefix>us-gaap</ElementPrefix>
      <IsBaseElement>true</IsBaseElement>
      <BalanceType>na</BalanceType>
      <PeriodType>duration</PeriodType>
      <ElementDataType>string</ElementDataType>
      <ShortDefinition>No definition available.</ShortDefinition>
      <IsReportTitle>false</IsReportTitle>
      <IsSegmentTitle>false</IsSegmentTitle>
      <IsSubReportEnd>false</IsSubReportEnd>
      <IsCalendarTitle>false</IsCalendarTitle>
      <IsTuple>false</IsTuple>
      <IsAbstractGroupTitle>false</IsAbstractGroupTitle>
      <IsEquityPrevioslyReportedAsRow>false</IsEquityPrevioslyReportedAsRow>
      <IsEquityAdjustmentRow>false</IsEquityAdjustmentRow>
      <IsBeginningBalance>false</IsBeginningBalance>
      <IsEndingBalance>false</IsEndingBalance>
      <IsReverseSign>false</IsReverseSign>
      <PreferredLabelRole>verboselabel</PreferredLabelRole>
      <IsEPS>false</IsEPS>
      <FootnoteIndexer />
      <Cells>
        <Cell>
          <Id>1</Id>
          <ShowCurrencySymbol>false</ShowCurrencySymbol>
          <IsNumeric>false</IsNumeric>
          <IsRatio>false</IsRatio>
          <DisplayZeroAsNone>false</DisplayZeroAsNone>
          <NumericAmount>0</NumericAmount>
          <RoundedNumericAmount>0</RoundedNumericAmount>
          <NonNumbericText>&lt;!--DOCTYPE html PUBLIC "-//W3C//DTD XHTML 1.0 Transitional//EN" "http://www.w3.org/TR/xhtml1/DTD/xhtml1-transitional.dtd" --&gt;
   &lt;!-- Begin Block Tagged Note 14 - us-gaap:ScheduleOfDefinedBenefitPlansDisclosuresTextBlock--&gt;
   &lt;div style="margin-left: 0%"&gt;
   &lt;div style="margin-top: 12pt; font-size: 1pt"&gt;&amp;#160;
   &lt;/div&gt;
   &lt;table width="100%" border="0" cellpadding="0" cellspacing="0" style="font-size: 10pt; font-family: Arial, Helvetica; color: #000000; background: #ffffff; text-align: left"&gt;
   &lt;tr&gt;
       &lt;td width="5%"&gt;&lt;/td&gt;
       &lt;td width="95%"&gt;&lt;/td&gt;
   &lt;/tr&gt;
   &lt;tr valign="top"&gt;
       &lt;td&gt;
       &lt;b&gt;&lt;font style="font-family: 'Times New Roman', Times"&gt;14.&amp;#160;&amp;#160;&lt;/font&gt;&lt;/b&gt;
   &lt;/td&gt;
       &lt;td&gt;
       &lt;b&gt;&lt;font style="font-family: 'Times New Roman', Times"&gt;Employees&amp;#8217;
       Defined Contribution Plan&lt;/font&gt;&lt;/b&gt;
   &lt;/td&gt;
   &lt;/tr&gt;
   &lt;/table&gt;
   &lt;div style="margin-top: 6pt; font-size: 1pt"&gt;&amp;#160;
   &lt;/div&gt;
   &lt;div align="left" style="margin-left: 0%; margin-right: 0%; text-indent: 4%; font-size: 10pt; font-family: 'Times New Roman', Times; color: #000000; background: #ffffff"&gt;
       The Company sponsors a defined contribution plan (the
       &amp;#8220;Savings Plan&amp;#8221;) for the benefit of substantially all
       of its U.S.&amp;#160;employees who meet certain eligibility
       requirements, primarily age and length of service. The Savings
       Plan allows employees to invest up to 60%, up to a maximum of
       $16.5 a year, of their eligible gross cash compensation
   invested on a pre-tax basis. The Company&amp;#8217;s optional
       contributions to the Savings Plan are generally in amounts based
       upon a certain percentage of the employees&amp;#8217; contributions.
       The Company&amp;#8217;s contributions to the Savings Plan during the
       52&amp;#160;weeks ended January&amp;#160;30, 2010, January&amp;#160;31, 2009
       and February&amp;#160;2, 2008, were $3,323, $2,736 and $2,235,
       respectively.
   &lt;/div&gt;
   &lt;/div&gt;
</NonNumbericText>
          <NonNumericTextHeader>&lt;!--DOCTYPE html PUBLIC "-//W3C//DTD XHTML 1.0 Transitional//EN" "http://www.w3.org/TR/xhtml1/DTD/xhtml1-transitional.dtd" --&gt;
   &lt;!-- Begin Block Tagged Note</NonNumericTextHeader>
          <FootnoteIndexer />
          <hasSegments>false</hasSegments>
          <hasScenarios>false</hasScenarios>
          <DisplayDateInUSFormat>false</DisplayDateInUSFormat>
        </Cell>
      </Cells>
      <OriginalInstanceReportColumns />
      <ElementDefenition>This element may be used to capture the entire disclosure for an employer that sponsors one or more defined benefit pension plans or one or more other defined benefit postretirement plans, of certain information, separately for pension plans and other postretirement benefit plans including the entity's schedule of fair value of plan assets for defined benefit or other postretirement plans.</ElementDefenition>
      <ElementReferences>Reference 1: http://www.xbrl.org/2003/role/presentationRef
 -Publisher FASB
 -Name Statement of Financial Accounting Standard (FAS)
 -Number 132R
 -Paragraph 5, 6, 7

Reference 2: http://www.xbrl.org/2003/role/presentationRef
 -Publisher FASB
 -Name Statement of Financial Accounting Standard (FAS)
 -Number 132R
 -Paragraph 5
 -Subparagraph d

Reference 3: http://www.xbrl.org/2003/role/presentationRef
 -Publisher FASB
 -Name Statement of Financial Accounting Standard (FAS)
 -Number 158
 -Paragraph 4, 7, 16, 20, 21

</ElementReferences>
      <IsTotalLabel>false</IsTotalLabel>
    </Row>
  </Rows>
  <Footnotes />
  <ComparabilityReport>false</ComparabilityReport>
  <NumberOfCols>1</NumberOfCols>
  <NumberOfRows>2</NumberOfRows>
  <HasScenarios>false</HasScenarios>
  <MonetaryRoundingLevel>UnKnown</MonetaryRoundingLevel>
  <SharesRoundingLevel>UnKnown</SharesRoundingLevel>
  <PerShareRoundingLevel>UnKnown</PerShareRoundingLevel>
  <HasPureData>false</HasPureData>
  <SharesShouldBeRounded>true</SharesShouldBeRounded>
</InstanceReport>
</XBRL>